{
  "items": [
    {
      "id": "documents",
      "title": "Документы",
      "type": "header"
    },
    {
      "id": "incomingDocuments",
      "title": "Входящие"
    },
    {
      "id": "outgoingDocuments",
      "title": "Исходящие"
    },
    {
      "id": "internalDocuments",
      "title": "Внутренние"
    },
    {
      "id": "incomingReviewTasks",
      "title": "На рассмотрение"
    },
    {
      "id": "incomingSignTasks",
      "title": "На подписание"
    },
    {
      "id": "myDocuments",
      "title": "Мои документы"
    },
    {
      "id": "documentTemplates",
      "title": "Шаблоны"
    },
    {
      "id": "incomingTasks",
      "title": "Входящие задачи",
      "type": "header"
    },
    {
      "id": "incomingExecutionTasks",
      "title": "На исполнение"
    },
    {
      "id": "incomingApprovalTasks",
      "title": "На согласование"
    },
    {
      "id": "incomingAcquaintanceTasks",
      "title": "На ознакомление"
    },
    {
      "id": "archivedIncomingTasks",
      "title": "Архив"
    },
    {
      "id": "outgoingTasks",
      "title": "Исходящие задачи",
      "type": "header"
    },
    {
      "id": "outgoingExecutionTasks",
      "title": "Исполнение"
    },
    {
      "id": "outgoingApprovalTasks",
      "title": "Согласование"
    },
    {
      "id": "outgoingAcquaintanceTasks",
      "title": "Ознакомление"
    },
    {
      "id": "archivedOutgoingTasks",
      "title": "Архив"
    },
    {
      "id": "archivedDocuments",
      "title": "Архив документов",
      "type": "header"
    }
  ]
}