{
  "title": "Вложения",
  "gridConfig": {
    "url": "app/searchfiles",
    "title": "Вложения",
    "columns": [
      {
        "id": "title",
        "title": "Вложение",
        "render": "file"
      },
      {
        "id": "created",
        "title": "Добавлен"
      },
      {
        "id": "authorTitle",
        "title": "Автор"
      },
      {
        "id": "objectTypeTitle",
        "title": "Тип объекта"
      },
      {
        "id": "objectTitle",
        "title": "Объект",
        "render": "link",
        "linkTypeColumn": "objectType",
        "idColumn": "objectId"
      }
    ]
  }
}